Metadata-Version: 2.1
Name: mashka
Version: 0.0.1
Summary: My Package
Author: Marya
Author-email: your@domain.com
